{
  "type": "FeatureCollection",
  "features": [
    {
      "type": "Feature",
      "properties": {
        "Event": "Yale Hacks 2015",
        "Role": "Participant",
        "Details": "Tic Tac Toe - A revolutionary new mobile game made by two noobs who learned a plethora of iOS knowledge in 36 hours."
      },
      "geometry": {
        "type": "Point",
        "coordinates": [
          41.313830,
          -72.930783
        ]
      }
    },
    {
      "type": "Feature",
      "properties": {
        "Event": "Yale Hacks 2017 ",
        "Role": "Participant",
        "Details": "Rolling Ball Unity Game - Objective is to roll a ball to collect points and win the game!"
      },
      "geometry": {
        "type": "Point",
        "coordinates": [
          41.313830,
          -72.930783
        ]
      }
    },
{
      "type": "Feature",
      "properties": {
        "Event": "Let's Talk Science Outreach",
        "Role": "Earth Scientist",
        "Details": "Presented science demonstration related to water density for kids at the Childern's Groundwater Festival at the Waterloo Region Museum. Name of talk was - Motion of the Ocean "
      },
      "geometry": {
        "type": "Point",
        "coordinates": [
          43.400806,
          -80.438239
        ]
      }
    },
    {
      "type": "Feature",
      "properties": {
        "Event": "Hack Duke 2014 #CodeForGood ",
        "Role": "Participant",
        "Details": "Largest collegiate hackathon addressing social good with four tracks: Inequality, energy, health, and education. Worked closely with non-profits, development organizations, and tech companies to address social issues and promote innovation and technology. "
      },
      "geometry": {
        "type": "Point",
        "coordinates": [
          36.003830,
          -78.941002
        ]
      }
    },
    {
      "type": "Feature",
      "properties": {
        "Event": "WHMIS and MSDS Training Canada system",
        "Role": "Workplace Training",
        "Details": "WHMIS - Workplace hazardous materialsinfrmation system for handling workplace hazardous controlled products. Trained in reading MSDS - Material Safety Data sheets."
      },
      "geometry": {
        "type": "Point",
        "coordinates": [
          43.470672,
          -80.541312
        ]
      }
    }
    ,
    {
      "type": "Feature",
      "properties": {
        "Event": "University of Waterloo ",
        "Role": "Teaching Assistant",
        "Details": "Technical Lab teaching assistant helping undergraduate students."
      },
      "geometry": {
        "type": "Point",
        "coordinates": [
          43.470672,
          -80.541312
        ]
      }
    }
    ,
    {
      "type": "Feature",
      "properties": {
        "Event": "Velocity Startup Incubator",
        "Role": "Residence/CEO/Entrepreneurship",
        "Details": "Accepted in Velocity Residence Program, worked in a startup in Communitech's Velocity Garage with access to mentors, funding, and startup resources. Met my velocity family. Best experience of my life :) "
      },
      "geometry": {
        "type": "Point",
        "coordinates": [
            43.466042,
            -80.542525
        ]
      }
    }
    ,
    
    {
      "type": "Feature",
      "properties": {
        "Event": "Junior Achievement of Canada",
        "Role": "Certificate of Accomplishment",
        "Details": "By providing youth with the skills necessary to become innovative, productive, and contributing citizens. Focusing on financial literacy, work readiness, and entrepreneurship."
      },
      "geometry": {
        "type": "Point",
        "coordinates": [
            43.646825,
            -79.378772
        ]
      }
    }
    ,
    {
      "type": "Feature",
      "properties": {
        "Event": "Y Combinator's Startup School NYC 2014",
        "Role": "Participant",
        "Details": "Accepted to YC's Startup School MC'ed by Alexis ohanian with speakers  Shana Fisher, Fred Wilson, Zach Sims, Kathryn Minshew, Apoorva, Sam Altman, and Garry Tan."
      },
      "geometry": {
        "type": "Point",
        "coordinates": [
          40.758161,
          -73.986158
        ]
      }
    }
    ,
    {
      "type": "Feature",
      "properties": {
        "Event": "Hack the North 2014",
        "Role": "Volunteer",
        "Details": "Part of original organizing team for Canada's biggest hackathon - Hack the North originating from Velocity Incubator. "
      },
      "geometry": {
        "type": "Point",
        "coordinates": [
            43.473110,
            -80.540117
        ]
      }
    }
    ,
    {
      "type": "Feature",
      "properties": {
        "Event": "Toronto Kairos Society Toronto",
        "Role": "Attendee",
        "Details": "Kairos Society is a global nonprofit organization that connects student entrepreneurs in the spaces of clean technology, healthcare, and education."
      },
      "geometry": {
        "type": "Point",
        "coordinates": [
          43.643459,
          -79.382240
        ]
      }
    }
    ,
    {
      "type": "Feature",
      "properties": {
        "Event": "Canadian Undergraduate Technology Conference 2016",
        "Role": "Presenter/Sponsor",
        "Details": "Represented the University of Waterloo's Hyperloop Team in the SpaceX competition. Gave technical presentation and demo's to undergraduate STEM students from all over the world at MaRS Discovery District."
      },
      "geometry": {
        "type": "Point",
        "coordinates": [
          43.660062,
          -79.388568

        ]
      }
    }
    ,
    {
      "type": "Feature",
      "properties": {
        "Event": "Microsoft Azure Machine Learning Contest 2016",
        "Role": "CUTC Participant",
        "Details": "Predictive modelling contest on building, scoring and evaluating a predictive model with Microsoft technical evangelists. Experiment model evaluation. Testing true positive, false natives, accuracy, precision using Microsoft Azure's Machine Learning Studio software."
      },
      "geometry": {
        "type": "Point",
        "coordinates": [
          43.660062,
          -79.388568

        ]
      }
    }
    ,
    {
      "type": "Feature",
      "properties": {
        "Event": "Hack Princeton 2016 and 2017",
        "Role": "Hacker",
        "Details": "Integrated a Microscoft Word add-on that allows audio parsing of the data. with Bing's speech text to speech API.  "
      },
      "geometry": {
        "type": "Point",
        "coordinates": [
            40.350507,
            -74.652696

        ]
      }
    }
     ,

    {
      "type": "Feature",
      "properties": {
        "Event": "Prospectors & Developers Association of Canada 2015/2016",
        "Role": "Member",
        "Details": "Four-day annual international convention held in Toronto, Canada for the minerals and mining industry attracting exhibitors, investors, analysts, mining executives, geologists and government officials. Attended technical sessions, short courses, and networking events."
      },
      "geometry": {
        "type": "Point",
        "coordinates": [
            43.644675,
            -79.385651

        ]
      }
    }
     ,

    {
      "type": "Feature",
      "properties": {
        "Event": "QuizUp Top 10 in California 2017",
        "Role": "Trivia Game Player",
        "Details": "Top 10 in California In Physics Trivia"
      },
      "geometry": {
        "type": "Point",
        "coordinates": [
            34.0693686,
            -118.4462365

        ]
      }
    }
     ,

    {
      "type": "Feature",
      "properties": {
        "Event": "Google's <Br/eak>Inequality Hackathon",
        "Role": "Participant",
        "Details": "Top 10 Hack at Google - CallAunty is an app which allows expectant mothers to call-in to determine if they are high risk and receive care."
      },
      "geometry": {
        "type": "Point",
        "coordinates": [
          43.454443,
          -80.498940
        ]
      }
    }
     ,


    {
      "type": "Feature",
      "properties": {
        "Event": "MHacks 8",
        "Role": "Participant",
        "Details": "Motion controlled hardware attachment to control common household devices like light bulbs, sound system, and more. One of my favorite hardware hacks."
      },
      "geometry": {
        "type": "Point",
        "coordinates": [
          42.341747,
          -83.060097
        ]
      }
    }
     ,

    {
      "type": "Feature",
      "properties": {
        "Event": "Perimeter Institute for Theoretical Physics 2018",
        "Role": "Invited researcher",
        "Details": "Network with graduate students, postdocs and faculty members in theoretical physics specifically in  cutting-edge research on condensed matter, cosmology, quantum fields/gravity/strings, and mathematical physics."
      },
      "geometry": {
        "type": "Point",
        "coordinates": [
          43.465396,
          -80.527540
        ]
      }
    }
     ,

    {
      "type": "Feature",
      "properties": {
        "Event": "Kairos Society Canada Charity Hackathon",
        "Role": "Attendee",
        "Details": " Invited by Kairos Society as an entrepreneur to help solve challenges where goverments and private industries have failed to innovate. Specifcally worked with The Salvation Army brainstorming ideas. Partnership with OCAD University."
      },
      "geometry": {
        "type": "Point",
        "coordinates": [
          43.653219,
          -79.391141
        ]
      }
    }
     ,

    {
      "type": "Feature",
      "properties": {
        "Event": "UC Berkeley's - She Started it",
        "Role": "Attendee",
        "Details": " Film Screening and panel discussion of the movie 'She Started it' - a movie about five young women who will stop at nothing to persue their startup dreams."
      },
      "geometry": {
        "type": "Point",
        "coordinates": [
          37.875161,
          -122.258284
        ]
      }
    }
     ,

    {
      "type": "Feature",
      "properties": {
        "Event": "Fireside Chat with Steve Wozniak",
         "Role": "Attendee",
        "Details": " Got waitlisted for tickets and lined up three hours in advance to get a front seat to see Steve Wozniak, co-founder of Apple Inc at University of San Francisco. 10/10 would do again :)"
      },
      "geometry": {
        "type": "Point",
        "coordinates": [
          37.777098,
          -122.449554
        ]
      }
    }
     ,


    {
      "type": "Feature",
      "properties": {
        "Event": "Mercedes-Benz Digital Challenge Berlin 2017",
        "Role": "Software developer",
        "Details": " Invited by Mercedes-Benz's Innovation Lab to be one of the first to start building with the 80+ mock APIs, SDKs and car emulators in an 8-week challenge."
      },
      "geometry": {
        "type": "Point",
        "coordinates": [
          52.509903,
          13.394262
        ]
      }
    }
     ,

    {
      "type": "Feature",
      "properties": {
        "Event": "SpaceX Hyperloop Engineering Design Competition 2016",
        "Role": "Waterloop Canadian Team",
        "Details": "Represented University of Waterloo's Canadian Team - Waterloop at the Hyperloop pod design competition at Texas A&M University. Comeptition where teams participating design and build a subscale prototype transport vehicle to demonstrate te technical feasibility of various aspects of Elon Musk's Hyperloop concept. Tesla and SpaceX engineers as judges."
      },
      "geometry": {
        "type": "Point",
        "coordinates": [
          30.610386,
          -96.340126
        ]
      }
    }
     ,

    {
      "type": "Feature",
      "properties": {
        "Event": "Bloomberg Terminal Certification (BMC) 2013/2014",
        "Role": "Finance Certification",
        "Details": "Completed an e-learning course that provides visual introduction to financial markets and the core functionality of the Bloomberg terminal.  "
      },
      "geometry": {
        "type": "Point",
        "coordinates": [
          43.468657,
          -80.541514

        ]
      }
    }
     ,


    {
      "type": "Feature",
      "properties": {
        "Event": "University of Waterloo ",
        "Role": "Electronic Media Coordinator",
        "Details": "Compiled bi-weekly web analysis reports using quantitative traffic stats from Google Analytics for the Marketing and Communications Department, Federation of Students. Re-designed the website with Wordpress CMS integration. "
      },
      "geometry": {
        "type": "Point",
        "coordinates": [
          43.471757,
          -80.545479

        ]
      }
    }
     ,



    {
      "type": "Feature",
      "properties": {
        "Event": "Students Offering Support National Office ",
        "Role": "Web Developer",
        "Details": "Developed dynamic websites using JavaScript, PHP, MySQL and MVC CodeIgniter Framework. Implemented an internal user search functionality using AJAX and JSON. "
      },
      "geometry": {
        "type": "Point",
        "coordinates": [
          43.667062,
          -79.403091

        ]
      }
    }
     ,




    {
      "type": "Feature",
      "properties": {
        "Event": "Geological Society of America",
        "Role": "GSA Professional Membership 9173757",
        "Details": " Membership access to geological-related articles for professionals teaching geology at the collegiate level. Access to publications and online journals like GSA Bullitin, Geology, and Lithosphere. "
      },
      "geometry": {
        "type": "Point",
        "coordinates": [
          40.037687,
          -105.250421

        ]
      }
    }
     ,

    {
      "type": "Feature",
      "properties": {
        "Event": "HACK THE 6iX 2018",
        "Role": "Mentor",
        "Details": "Technical mentor for event with approximately 400 hackers at Toronto’s largest summer hackathon. Lit."
      },
      "geometry": {
        "type": "Point",
        "coordinates": [
          43.668847,
          -79.393242

        ]
      }
    }
  ]
}
